{
    "year1": {
        "ISiT": [
            "Elektronsko poslovanje (NA)",
            "Matematika 1",
            "Francuski jezik u informatici",
            "Ekonomija",
            "Engleski jezik u informatici",
            "Osnove informaciono komunikacionih tehnologija",
            "Menadžment",
            "Osnovi organizacije"
        ],
        "MiO": [
            "Matematika 1",
            "Francuski jezik u informatici",
            "Ekonomija",
            "Osnove informaciono komunikacionih tehnologija",
            "Menadžment",
            "Osnovi organizacije"
        ]
    },
    "year2": {
        "ISiT": [
            "Matematika 3",
            "Marketing",
            "Upravljanje projektima",
            "Programiranje 1 (NA)",
            "Teorija verovatnoće",
            "Arhitektura računara i operativni sistemi",
            "Diskretne matematičke strukture"
        ],
        "MiO": [
            "Menadžment ljudskih resursa",
            "Marketing",
            "Osnove kvaliteta",
            "Računovodstvo",
            "Teorija verovatnoće"
        ]
    },
    "year3": {
        "ISiT": [
            "Računarske mreže i telekomunikacije",
            "Operaciona istraživanja 1",
            "Projektovanje informacionih sistema",
            "Projektovanje softvera (C#)",
            "Teorija sistema",
            "Projektovanje softvera"
        ],
        "Finansijski menadžment": [
            "Elektronsko poslovanje (NA)",
            "Korporativne komunikacije",
            "Osnove finansijskog menadžmenta",
            "Upravljanje projektima",
            "Operaciona istraživanja 1"
        ],
        "Lin organizacija poslovanja": [
            "Osnove finansijskog menadžmenta",
            "Upravljanje projektima",
            "Industrijsko i menadžment inženjerstvo",
            "Operaciona istraživanja 1",
            "Lin proizvodnja i usluge"
        ],
        "Menadžment kvaliteta i standardizacija": [
            "Osnove finansijskog menadžmenta",
            "Upravljanje projektima",
            "Operaciona istraživanja 1",
            "Upravljanje kvalitetom",
            "Teorija odlučivanja"
        ],
        "Marketing menadžment i komunikacije": [
            "Elektronsko poslovanje (NA)",
            "Korporativne komunikacije",
            "Osnove finansijskog menadžmenta",
            "Upravljanje projektima",
            "Operaciona istraživanja 1"
        ],
        "Operacioni menadžment": [
            "Osnove finansijskog menadžmenta",
            "Industrijsko i menadžment inženjerstvo",
            "Operaciona istraživanja 1",
            "Lean logistika",
            "Upravljački sistemi"
        ],
        "Projektni menadžment": [
            "Osnove finansijskog menadžmenta",
            "Upravljanje projektima",
            "Operaciona istraživanja 1",
            "Lin proizvodnja i usluge",
            "Teorija odlučivanja"
        ]
    },
    "year4": {
        "ISiT": [
            "Programiranje 3",
            "Internet tehnologije",
            "Multimediji",
            "Mobilno poslovanje",
            "Projektovanje informacionih sistema",
            "Simulacija i simulacioni jezici",
            "Projektovanje softvera (C#)",
            "Napredne .NET tehnologije",
            "Projektovanje softvera",
            "Dinamika organizacionih sistema",
            "Dizajn korisničkog interfejsa"
        ],
        "Men": [
            "Veštine i tehnike poslovne komunikacije",
            "Međunarodni menadžment",
            "Preduzetništvo",
            "Uvod u finansijska tržišta",
            "Poslovna inteligencija",
            "Strateški marketing"
        ],
        "OM": [
            "Kontinualno poboljšavanje proizvodnje",
            "Dizajn za životnu sredinu",
            "Informacioni sistemi preduzeća",
            "Računarski integrisana proizvodnja",
            "Menadžment ključnih performansi proizvodnje",
            "Analiza pouzdanosti i rizika",
            "Intelektualna svojina",
            "Planiranje proizvodnje i usluga"
        ],
        "MKS": [
            "Sistem kvaliteta životne sredine",
            "Analiza pouzdanosti i rizika",
            "Upravljanje projektima",
            "Inženjering kvaliteta",
            "Poslovni informacioni sistemi",
            "Menadžment totalnog kvaliteta",
            "Odabrana poglavlja iz menadžmenta kvaliteta 1",
            "Sistem menadžmenta zdravlja i bezbednosti na radu"
        ]
    }
}